MANIFEST.in
README.rst
setup.cfg
setup.py
django_person.egg-info/PKG-INFO
django_person.egg-info/SOURCES.txt
django_person.egg-info/dependency_links.txt
django_person.egg-info/top_level.txt
people/__init__.py
people/admin.py
people/apps.py
people/forms.py
people/models.py
people/tests.py
people/urls.py
people/views.py
people/migrations/0001_initial.py
people/migrations/__init__.py